<?xml version="1.0" encoding="utf-8" ?>
<Defs>

  <ThingDef ParentName="BodyPartBionicBase">
    <defName>BionicReproductiveOrgans</defName>
    <label>bionic reproductive organs</label>
    <description>Provide phenomenal stamina and boost fertility.</description>    
    <descriptionHyperlinks><RecipeDef>InstallBionicReproductiveOrgans</RecipeDef></descriptionHyperlinks>
    <costList>
      <Plasteel>15</Plasteel>
      <ComponentSpacer>4</ComponentSpacer>
      <Chemfuel>10</Chemfuel>
    </costList>
    <thingSetMakerTags><li>RewardStandardMidFreq</li></thingSetMakerTags>
    <statBases>
      <Mass>0.5</Mass>
    </statBases>
  </ThingDef>

</Defs>
  